grimoirelab/core/__init__.py
grimoirelab/core/_version.py
grimoirelab/core/app/__init__.py
grimoirelab/core/app/asgi.py
grimoirelab/core/app/urls.py
grimoirelab/core/app/wsgi.py
grimoirelab/core/config/__init__.py
grimoirelab/core/config/settings.py
grimoirelab/core/consumers/__init__.py
grimoirelab/core/consumers/archivist.py
grimoirelab/core/consumers/consumer.py
grimoirelab/core/consumers/consumer_pool.py
grimoirelab/core/consumers/identities.py
grimoirelab/core/datasources/__init__.py
grimoirelab/core/datasources/api.py
grimoirelab/core/datasources/apps.py
grimoirelab/core/datasources/migrations/0001_initial.py
grimoirelab/core/datasources/migrations/0002_ecosystem.py
grimoirelab/core/datasources/migrations/0003_project.py
grimoirelab/core/datasources/migrations/0004_dataset.py
grimoirelab/core/datasources/migrations/0005_generate_uuids.py
grimoirelab/core/datasources/migrations/0006_alter_repository_unique.py
grimoirelab/core/datasources/migrations/__init__.py
grimoirelab/core/datasources/models.py
grimoirelab/core/datasources/urls.py
grimoirelab/core/datasources/utils.py
grimoirelab/core/models.py
grimoirelab/core/permissions.py
grimoirelab/core/runner/__init__.py
grimoirelab/core/runner/cmd.py
grimoirelab/core/runner/commands/__init__.py
grimoirelab/core/runner/commands/admin.py
grimoirelab/core/runner/commands/run.py
grimoirelab/core/scheduler/__init__.py
grimoirelab/core/scheduler/api.py
grimoirelab/core/scheduler/apps.py
grimoirelab/core/scheduler/db.py
grimoirelab/core/scheduler/errors.py
grimoirelab/core/scheduler/jobs.py
grimoirelab/core/scheduler/models.py
grimoirelab/core/scheduler/scheduler.py
grimoirelab/core/scheduler/tasks/__init__.py
grimoirelab/core/scheduler/tasks/apps.py
grimoirelab/core/scheduler/tasks/chronicler.py
grimoirelab/core/scheduler/tasks/migrations/0001_initial.py
grimoirelab/core/scheduler/tasks/migrations/0002_storagetask_storagejob.py
grimoirelab/core/scheduler/tasks/migrations/0003_job_started_at.py
grimoirelab_core-0.1.0.dist-info/METADATA
grimoirelab_core-0.1.0.dist-info/WHEEL
grimoirelab_core-0.1.0.dist-info/entry_points.txt
grimoirelab_core-0.1.0.dist-info/licenses/AUTHORS
grimoirelab_core-0.1.0.dist-info/licenses/LICENSE
grimoirelab_core-0.1.0.dist-info/RECORD
