Metadata-Version: 2.4
Name: grimoirelab-core
Version: 0.1.0
Summary: Core of GrimoireLab
License: GPL-3.0+
License-File: AUTHORS
License-File: LICENSE
Keywords: development,grimoirelab
Author: GrimoireLab Developers
Requires-Python: >=3.11,<4.0
Classifier: Development Status :: 4 - Beta
Classifier: Intended Audience :: Developers
Classifier: License :: OSI Approved :: GNU General Public License v3 or later (GPLv3+)
Classifier: Programming Language :: Python :: 3
Classifier: Programming Language :: Python :: 3.11
Classifier: Programming Language :: Python :: 3.12
Classifier: Programming Language :: Python :: 3.13
Classifier: Programming Language :: Python :: 3.14
Classifier: Topic :: Software Development
Requires-Dist: django (>=5.2,<6.0)
Requires-Dist: django-cors-headers (>=4.6.0,<5.0.0)
Requires-Dist: django-rq (>=3.1,<4.0)
Requires-Dist: django-storages[google] (>=1.14.6,<2.0.0)
Requires-Dist: djangorestframework (>=3.15.2,<4.0.0)
Requires-Dist: djangorestframework-simplejwt (>=5.4.0,<6.0.0)
Requires-Dist: drf-spectacular (>=0.28.0,<0.29.0)
Requires-Dist: grimoirelab-chronicler (>=0.0.1rc2)
Requires-Dist: grimoirelab-toolkit (>=1.2.0)
Requires-Dist: mysqlclient (>=2.0.3,<3.0.0)
Requires-Dist: opensearch-py (>=3.0.0,<4.0.0)
Requires-Dist: perceval (>=1.3.4)
Requires-Dist: sortinghat (>=1.11.0)
Requires-Dist: uWSGI (>=2.0,<3.0)
Project-URL: Bug Tracker, https://github.com/chaoss/grimoirelab-core/issues
Project-URL: Homepage, https://chaoss.github.io/grimoirelab/
Project-URL: Repository, https://github.com/chaoss/grimoirelab-core
